generator/__init__.py
generator/__main__.py
generator/generate.py
generator/git.py
generator/main.py
generator/reader.py
generator/utils.py
generator/yaml.py
terragrunt_generator-0.17.0.dist-info/licenses/COPYING
tests/__init__.py
tests/test_cli.py
tests/test_generate.py
tests/test_git.py
tests/test_reader.py
tests/test_utils.py
tests/test_yaml.py
terragrunt_generator-0.17.0.dist-info/METADATA
terragrunt_generator-0.17.0.dist-info/WHEEL
terragrunt_generator-0.17.0.dist-info/entry_points.txt
terragrunt_generator-0.17.0.dist-info/top_level.txt
terragrunt_generator-0.17.0.dist-info/RECORD
