Metadata-Version: 2.4
Name: terragrunt-generator
Version: 0.17.0
Summary: generate terragrunt manifest from terraform module.
Author: Chris
Author-email: goabonga@pm.me
License-File: COPYING
Requires-Dist: python-hcl2==4.3.5
Requires-Dist: GitPython==3.1.43
Provides-Extra: dev
Requires-Dist: pytest==8.3.3; extra == "dev"
Requires-Dist: pytest-cov==5.0.0; extra == "dev"
Requires-Dist: black==24.8.0; extra == "dev"
Requires-Dist: isort==5.13.2; extra == "dev"
Requires-Dist: commitizen==3.29.0; extra == "dev"
Requires-Dist: flake8==7.1.1; extra == "dev"
Requires-Dist: pre-commit==3.8.0; extra == "dev"
Dynamic: author
Dynamic: author-email
Dynamic: description
Dynamic: description-content-type
Dynamic: license-file
Dynamic: provides-extra
Dynamic: requires-dist
Dynamic: summary
